{
  "keystone": [
    "Grasp of the Undying",
    "Fleet Footwork",
    "Conqueror",
    "Lethal Tempo",
    "Arcane Comet",
    "Glacial Augment",
    "Electrocute",
    "Dark Harvest",
    "Phase Rush",
    "Aftershock",
    "Empowerment",
    "Aery",
    "First Strike"
  ],
  "precision": [
    "Brutal",
    "Gathering Storm",
    "Legend: Alacrity",
    "Giant Slayer",
    "Triumph",
    "Coup de Grace",
    "Legend: Bloodline",
    "Last Stand",
    "Legend: Tenacity"
  ],
  "domination": [
    "Sudden Impact",
    "Zombie Ward",
    "Scorch",
    "Chain Assault",
    "Eyeball Collector",
    "Cheap Shot",
    "Tyrant",
    "Ingenious Hunter",
    "Empowered Attack",
    "Psychic Wave",
    "Shield Bash"
  ],
  "inspiration": [
    "Transcendence",
    "Ixtali Seedjar",
    "Sweet Tooth",
    "Hextech Flashtraption",
    "Nimbus Cloak",
    "Demolish",
    "Celerity",
    "Axiom Arcanist",
    "Future's Market",
    "Item Crafting",
    "Manaflow Band"
  ],
  "resolve": [
    "Second Wind",
    "Nullifying Orb",
    "Overgrowth",
    "Bone Plating",
    "Perseverance",
    "Unshakeable",
    "Font of Life",
    "Courage of the Colossus",
    "Revitalize",
    "Loyalty"
  ]
}